Metadata-Version: 2.1
Name: pozalabs-dependeny-injector
Version: 4.42.0
Summary: 
License: BSD New
Keywords: Dependency injection,DI,Inversion of Control,IoC,Factory,Singleton,Design patterns,Flask
Author: pozalabs
Author-email: contact@pozalabs.com
Requires-Python: >=3.11,<4.0
Classifier: Development Status :: 5 - Production/Stable
Classifier: Framework :: AsyncIO
Classifier: Framework :: Bottle
Classifier: Framework :: Django
Classifier: Framework :: Flask
Classifier: Framework :: Pylons
Classifier: Framework :: Pyramid
Classifier: Framework :: Pytest
Classifier: Framework :: TurboGears
Classifier: Intended Audience :: Developers
Classifier: License :: OSI Approved :: BSD License
Classifier: License :: Other/Proprietary License
Classifier: Operating System :: OS Independent
Classifier: Programming Language :: Python
Classifier: Programming Language :: Python :: 3
Classifier: Programming Language :: Python :: 3.11
Classifier: Programming Language :: Python :: 3.12
Classifier: Programming Language :: Python :: Implementation :: CPython
Classifier: Programming Language :: Python :: Implementation :: PyPy
Classifier: Topic :: Software Development
Classifier: Topic :: Software Development :: Libraries
Classifier: Topic :: Software Development :: Libraries :: Python Modules
